LICENSE
MANIFEST.in
setup.py
TranscriptBot.egg-info/PKG-INFO
TranscriptBot.egg-info/SOURCES.txt
TranscriptBot.egg-info/dependency_links.txt
TranscriptBot.egg-info/pbr.json
TranscriptBot.egg-info/requires.txt
TranscriptBot.egg-info/top_level.txt
bin/transcriptbot
transcriptbot/__init__.py
transcriptbot/db.py
transcriptbot/recorder.py
transcriptbot/slack.py
transcriptbot/transcriber.py