Metadata-Version: 1.0
Name: TranscriptBot
Version: 0.1.2
Summary: Real-time voice transcription Slack bot
Home-page: https://github.com/agermanidis/TranscriptBot
Author: Anastasis Germanidis
Author-email: agermanidis@gmail.com
License: The MIT License (MIT)
